dexteritysdk/.DS_Store
dexteritysdk/__init__.py
dexteritysdk/bots/bootstrap.py
dexteritysdk/bots/consume_events_crank.py
dexteritysdk/bots/expiration_routine.py
dexteritysdk/bots/new_connect.py
dexteritysdk/bots/oracle_price_crank.py
dexteritysdk/bots/quoter_bot.py
dexteritysdk/bots/settle_crank.py
dexteritysdk/bots/solmate_bootstrap.py
dexteritysdk/bots/taker_bot.py
dexteritysdk/codegen/__init__.py
dexteritysdk/codegen/alpha_risk_engine/__init__.py
dexteritysdk/codegen/alpha_risk_engine/accounts.py
dexteritysdk/codegen/alpha_risk_engine/addrs.py
dexteritysdk/codegen/alpha_risk_engine/instructions/__init__.py
dexteritysdk/codegen/alpha_risk_engine/instructions/create_risk_state_account.py
dexteritysdk/codegen/alpha_risk_engine/instructions/instruction_tag.py
dexteritysdk/codegen/alpha_risk_engine/instructions/validate_account_health.py
dexteritysdk/codegen/alpha_risk_engine/instructions/validate_account_liquidation.py
dexteritysdk/codegen/alpha_risk_engine/types/__init__.py
dexteritysdk/codegen/alpha_risk_engine/types/health.py
dexteritysdk/codegen/dex/__init__.py
dexteritysdk/codegen/dex/__init__.py.py
dexteritysdk/codegen/dex/accounts.py
dexteritysdk/codegen/dex/addrs.py
dexteritysdk/codegen/dex/constants.py
dexteritysdk/codegen/dex/instructions/__init__.py
dexteritysdk/codegen/dex/instructions/cancel_all.py
dexteritysdk/codegen/dex/instructions/cancel_order.py
dexteritysdk/codegen/dex/instructions/choose_successor.py
dexteritysdk/codegen/dex/instructions/claim_authority.py
dexteritysdk/codegen/dex/instructions/clear_expired_orderbook.py
dexteritysdk/codegen/dex/instructions/clear_open_orders.py
dexteritysdk/codegen/dex/instructions/close_trader_risk_group.py
dexteritysdk/codegen/dex/instructions/consume_orderbook_events.py
dexteritysdk/codegen/dex/instructions/deactivate_market_product.py
dexteritysdk/codegen/dex/instructions/deposit_funds.py
dexteritysdk/codegen/dex/instructions/disable_killswitch.py
dexteritysdk/codegen/dex/instructions/enable_killswitch.py
dexteritysdk-0.2.50.dist-info/entry_points.txt
dexteritysdk-0.2.50.dist-info/WHEEL
dexteritysdk-0.2.50.dist-info/METADATA
dexteritysdk-0.2.50.dist-info/RECORD
